setup.py
OpenMI_OpenGMS_Engine/__init__.py
OpenMI_OpenGMS_Engine/openmiOpengmsEngine.py
OpenMI_OpenGMS_Engine.egg-info/PKG-INFO
OpenMI_OpenGMS_Engine.egg-info/SOURCES.txt
OpenMI_OpenGMS_Engine.egg-info/dependency_links.txt
OpenMI_OpenGMS_Engine.egg-info/requires.txt
OpenMI_OpenGMS_Engine.egg-info/top_level.txt
OpenMI_OpenGMS_Engine.egg-info/zip-safe
OpenMI_OpenGMS_Engine/mdl_python/AttributeSet.py
OpenMI_OpenGMS_Engine/mdl_python/Behavior.py
OpenMI_OpenGMS_Engine/mdl_python/IAttributeSet.py
OpenMI_OpenGMS_Engine/mdl_python/IBehavior.py
OpenMI_OpenGMS_Engine/mdl_python/IModelClass.py
OpenMI_OpenGMS_Engine/mdl_python/IRuntime.py
OpenMI_OpenGMS_Engine/mdl_python/ModelClass.py
OpenMI_OpenGMS_Engine/mdl_python/Runtime.py
OpenMI_OpenGMS_Engine/mdl_python/__init__.py
OpenMI_OpenGMS_Engine/mdl_python/mdl_test.py
OpenMI_OpenGMS_Engine/resource/ICSharpCode.SharpZipLib.dll
OpenMI_OpenGMS_Engine/resource/NJModelServiceSDK.dll
OpenMI_OpenGMS_Engine/resource/Newtonsoft.Json.dll
OpenMI_OpenGMS_Engine/resource/Oatc.OpenMI.Sdk.Backbone.dll
OpenMI_OpenGMS_Engine/resource/Oatc.OpenMI.Sdk.Buffer.dll
OpenMI_OpenGMS_Engine/resource/Oatc.OpenMI.Sdk.DevelopmentSupport.dll
OpenMI_OpenGMS_Engine/resource/Oatc.OpenMI.Sdk.Spatial.dll
OpenMI_OpenGMS_Engine/resource/Oatc.OpenMI.Sdk.Wrapper.dll
OpenMI_OpenGMS_Engine/resource/OpenGMS.OpenMI.Case.dll
OpenMI_OpenGMS_Engine/resource/OpenMI.Standard.dll
OpenMI_OpenGMS_Engine/resource/OpenMIOpenGMSWrapper.exe
OpenMI_OpenGMS_Engine/resource/OpenMI_Interoperation.dll
OpenMI_OpenGMS_Engine/resource/nxdat.csharp.dll
OpenMI_OpenGMS_Engine/resource/nxmodel.mdl.csharp.dll
OpenMI_OpenGMS_Engine/resource/openmi_resource/license.txt
OpenMI_OpenGMS_Engine/resource/openmi_resource/wrapper/ICSharpCode.SharpZipLib.dll
OpenMI_OpenGMS_Engine/resource/openmi_resource/wrapper/NJModelServiceSDK.dll
OpenMI_OpenGMS_Engine/resource/openmi_resource/wrapper/Newtonsoft.Json.dll
OpenMI_OpenGMS_Engine/resource/openmi_resource/wrapper/Oatc.OpenMI.Gui.Controls.dll
OpenMI_OpenGMS_Engine/resource/openmi_resource/wrapper/Oatc.OpenMI.Gui.Core.dll
OpenMI_OpenGMS_Engine/resource/openmi_resource/wrapper/Oatc.OpenMI.Sdk.Backbone.dll
OpenMI_OpenGMS_Engine/resource/openmi_resource/wrapper/Oatc.OpenMI.Sdk.Buffer.dll
